{
  "language": "lv",
  "title": "Omar's theme",
  "artist": "Pet Shop Boys",
  "slug": "omar-s-theme-pet-shop-boys",
  "track_length_seconds": 188,
  "source": {
    "provider": "musixmatch",
    "track_id": 215810472,
    "commontrack_id": 126916481,
    "track_share_url": "https://www.musixmatch.com/lyrics/Pet-Shop-Boys/Omar-s-theme?utm_source=application&utm_campaign=api&utm_medium=Verite+Solutions%3A1409626224320",
    "track_edit_url": "https://www.musixmatch.com/lyrics/Pet-Shop-Boys/Omar-s-theme/edit?utm_source=application&utm_campaign=api&utm_medium=Verite+Solutions%3A1409626224320",
    "search_language": "lv",
    "fetched_at": "2025-11-22T09:26:14.698930Z"
  }
}