{
  "language": "gd",
  "title": "Smeorach Chlann Domhnaill (The Mavis of Clan Donald)",
  "artist": "Julie Fowlis",
  "slug": "smeorach-chlann-domhnaill-the-mavis-of-clan-donald-julie-fowlis",
  "track_length_seconds": 252,
  "source": {
    "provider": "musixmatch",
    "track_id": 54252775,
    "commontrack_id": 17089485,
    "track_share_url": "https://www.musixmatch.com/lyrics/Julie-Fowlis/Smeorach-Chlann-Domhnaill-The-Mavis-Of-Clan-Donald?utm_source=application&utm_campaign=api&utm_medium=Verite+Solutions%3A1409626224320",
    "track_edit_url": "https://www.musixmatch.com/lyrics/Julie-Fowlis/Smeorach-Chlann-Domhnaill-The-Mavis-Of-Clan-Donald/edit?utm_source=application&utm_campaign=api&utm_medium=Verite+Solutions%3A1409626224320",
    "search_language": "gd",
    "fetched_at": "2025-11-22T09:13:04.512570Z"
  }
}