{
  "language": "ru",
  "title": "Life",
  "artist": "Zivert",
  "slug": "life-zivert",
  "track_length_seconds": 188,
  "source": {
    "provider": "musixmatch",
    "track_id": 173919790,
    "commontrack_id": 90119896,
    "track_share_url": "https://www.musixmatch.com/lyrics/Zivert/Life?utm_source=application&utm_campaign=api&utm_medium=Verite+Solutions%3A1409626224320",
    "track_edit_url": "https://www.musixmatch.com/lyrics/Zivert/Life/edit?utm_source=application&utm_campaign=api&utm_medium=Verite+Solutions%3A1409626224320",
    "search_language": "ru",
    "fetched_at": "2025-11-22T09:31:19.461962Z"
  }
}